MotorSonic/motorSonic.v
module motorSonic
 (input i_Reset,
  input i_Clk,
  input i_sonic_izq,
  input i_sonic_der,
  output normal,
  output giro_izq,
  output giro_der);
  localparam s0 = 2'b00; //Normal (ir derecho)
  localparam s1 = 2'b01; //Giro Derecha
  localparam s2 = 2'b10; //Giro Izquierda
  reg [1:0] r_Estado_Actual;
  
  always @(posedge i_Clk or posedge i_Reset)
  begin
    if (i_Reset)
      r_Estado_Actual <= s0;
    else
    begin
      case (r_Estado_Actual)
        s0:
          if (i_sonic_izq == 1 & i_sonic_der == 1)
            r_Estado_Actual <= s0;
        else if (i_sonic_izq == 1 & i_sonic_der == 0)
            r_Estado_Actual <= s1;
        else if (i_sonic_izq == 0 & i_sonic_der == 1)
            r_Estado_Actual <= s2;
        else if (i_sonic_izq == 0 & i_sonic_der == 0)
            r_Estado_Actual <= s0;

        s1:
          if (i_sonic_izq == 1 & i_sonic_der == 1)
            r_Estado_Actual <= s0;
        else if (i_sonic_izq == 1 & i_sonic_der == 0)
            r_Estado_Actual <= s1;
        else if (i_sonic_izq == 0 & i_sonic_der == 1)
            r_Estado_Actual <= s2;
        else if (i_sonic_izq == 0 & i_sonic_der == 0)
            r_Estado_Actual <= s0;

        s2:
          if (i_sonic_izq == 1 & i_sonic_der == 1)
            r_Estado_Actual <= s0;
        else if (i_sonic_izq == 1 & i_sonic_der == 0)
            r_Estado_Actual <= s1;
        else if (i_sonic_izq == 0 & i_sonic_der == 1)
            r_Estado_Actual <= s2;
        else if (i_sonic_izq == 0 & i_sonic_der == 0)
            r_Estado_Actual <= s0;
      endcase
    end
  end
  assign normal = (r_Estado_Actual == s0);
  assign giro_der = (r_Estado_Actual == s1);
  assign giro_izq = (r_Estado_Actual == s2);
endmodule

MotorSonic/motorSonic_tb.v
`include "motorSonic.v"
`timescale 1 ns / 1 ns

module motorSonic_tb();

  reg r_Reset = 1'b1, r_Clk = 1'b0, r_sonic_izq = 1'b0, r_sonic_der = 1'b0;
  wire w_normal, w_giro_izq, w_giro_der;

    motorSonic UUT
   (.i_Reset(r_Reset),
    .i_Clk(r_Clk), 
    .i_sonic_izq(r_sonic_izq),
    .i_sonic_der(r_sonic_der),
    .normal(w_normal),
    .giro_izq(w_giro_izq),
    .giro_der(w_giro_der));
  
  always #1 r_Clk <= !r_Clk;

  initial begin
    $dumpfile("motorSonic_tb.vcd"); 
    $dumpvars;
    #10;
    r_Reset <= 1'b0;
    #10;
    assert (w_normal == 1'b1);
    r_sonic_izq <= 1'b0;
    r_sonic_der <= 1'b1;
    #10;
    assert (w_giro_der == 1'b1);
    r_sonic_izq <= 1'b1;
    r_sonic_der <= 1'b1;
    #10;
    assert (w_giro_izq == 1'b1);
    r_sonic_izq <= 1'b1;
    r_sonic_der <= 1'b0;
    #10;
    assert (w_giro_izq == 1'b1);
    r_sonic_izq <= 1'b0;
    r_sonic_der <= 1'b0;
    #10;
    assert (w_giro_der == 1'b1);
    r_sonic_izq <= 1'b1;
    r_sonic_der <= 1'b0;
    #10;
    assert (w_giro_der == 1'b1);
    r_sonic_izq <= 1'b1;
    r_sonic_der <= 1'b1;
    #10;
    assert (w_normal == 1'b1);
    $finish();
  end
endmodule
//iverilog -g2012 -o TM_TB.vvp TM_TB.v

MotorSonic/motorSonic_tb.vcd
$date
	Mon May 20 11:52:23 2024
$end
$version
	Icarus Verilog
$end
$timescale
	1ns
$end
$scope module motorSonic_tb $end
$var wire 1 ! w_normal $end
$var wire 1 " w_giro_izq $end
$var wire 1 # w_giro_der $end
$var reg 1 $ r_Clk $end
$var reg 1 % r_Reset $end
$var reg 1 & r_sonic_der $end
$var reg 1 ' r_sonic_izq $end
$scope module UUT $end
$var wire 1 $ i_Clk $end
$var wire 1 % i_Reset $end
$var wire 1 & i_sonic_der $end
$var wire 1 ' i_sonic_izq $end
$var wire 1 ! normal $end
$var wire 1 " giro_izq $end
$var wire 1 # giro_der $end
$var parameter 2 ( s0 $end
$var parameter 2 ) s1 $end
$var parameter 2 * s2 $end
$var reg 2 + r_Estado_Actual [1:0] $end
$upscope $end
$upscope $end
$enddefinitions $end
$comment Show the parameter values. $end
$dumpall
b10 *
b1 )
b0 (
$end
#0
$dumpvars
bx +
0'
0&
1%
0$
x#
x"
x!
$end
#1
1!
0#
0"
b0 +
1$
#2
0$
#3
1$
#4
0$
#5
1$
#6
0$
#7
1$
#8
0$
#9
1$
#10
0$
0%
#11
1$
#12
0$
#13
1$
#14
0$
#15
1$
#16
0$
#17
1$
#18
0$
#19
1$
#20
0$
1&
#21
0!
1"
b10 +
1$
#22
0$
#23
1$
#24
0$
#25
1$
#26
0$
#27
1$
#28
0$
#29
1$
#30
0$
1'
#31
1!
0"
b0 +
1$
#32
0$
#33
1$
#34
0$
#35
1$
#36
0$
#37
1$
#38
0$
#39
1$
#40
0$
0&
#41
0!
1#
b1 +
1$
#42
0$
#43
1$
#44
0$
#45
1$
#46
0$
#47
1$
#48
0$
#49
1$
#50
0$
0'
#51
1!
0#
b0 +
1$
#52
0$
#53
1$
#54
0$
#55
1$
#56
0$
#57
1$
#58
0$
#59
1$
#60
0$
1'
#61
0!
1#
b1 +
1$
#62
0$
#63
1$
#64
0$
#65
1$
#66
0$
#67
1$
#68
0$
#69
1$
#70
0$
1&
#71
1!
0#
b0 +
1$
