PWM/pwm.v
`timescale 1ns/1ns

module pwm (
    input clk,
    output [3:0] led //Se usan leds para ver si funciona el codigo correctamente
);
//Contador para hacer un comparador mas adelante

reg [6:0] contador = 0; //log_2(100) = 6.64 aprox 7
always @(posedge clk) begin
    if (contador < 100)
        contador <= contador + 1;
    else contador <= 0; // resetear contador 
end

//20% ciclo de trabajo (duty cycle)
assign led[0] = (contador < 20) ? 1:0; //Si el contador es menor a 20 se la asigna valor de 1 al led, sino se le asigna 0

//40% ciclo de trabajo (duty cycle)
assign led[1] = (contador < 40) ? 1:0;

//60% ciclo de trabajo (duty cycle)
assign led[2] = (contador < 60) ? 1:0;

//80% ciclo de trabajo (duty cycle)
assign led[3] = (contador < 80) ? 1:0;    
endmodule

PWM/pwm_tb.v
`timescale 1ns/1ns
`include "pwm.v"

module pwm_tb;
    integer i;
    reg clk = 0;
    wire [3:0] led;
    pwm uut(clk, led);
  initial begin
  
	$dumpfile("pwm.vcd");
	$dumpvars(0,pwm_tb);

  for(i=0; i<1000; i = i+1) begin
        clk = ~clk;
        #10; //Tiempo total del testbech 10 ns
    end

	$display("Test Finished uwu");
	$finish;
  end
endmodule

PWM/pwm.vcd
$date
	Thu Mar 28 11:24:13 2024
$end
$version
	Icarus Verilog
$end
$timescale
	1ns
$end
$scope module pwm_tb $end
$var wire 4 ! led [3:0] $end
$var reg 1 " clk $end
$var integer 32 # i [31:0] $end
$scope module uut $end
$var wire 1 " clk $end
$var wire 4 $ led [3:0] $end
$var reg 7 % contador [6:0] $end
$upscope $end
$upscope $end
$enddefinitions $end
$comment Show the parameter values. $end
$dumpall
$end
#0
$dumpvars
b1 %
b1111 $
b0 #
1"
b1111 !
$end
#10
0"
b1 #
#20
b10 %
1"
b10 #
#30
0"
b11 #
#40
b11 %
1"
b100 #
#50
0"
b101 #
#60
b100 %
1"
b110 #
#70
0"
b111 #
#80
b101 %
1"
b1000 #
#90
0"
b1001 #
#100
b110 %
1"
b1010 #
#110
0"
b1011 #
#120
b111 %
1"
b1100 #
#130
0"
b1101 #
#140
b1000 %
1"
b1110 #
#150
0"
b1111 #
#160
b1001 %
1"
b10000 #
#170
0"
b10001 #
#180
b1010 %
1"
b10010 #
#190
0"
b10011 #
#200
b1011 %
1"
b10100 #
#210
0"
b10101 #
#220
b1100 %
1"
b10110 #
#230
0"
b10111 #
#240
b1101 %
1"
b11000 #
#250
0"
b11001 #
#260
b1110 %
1"
b11010 #
#270
0"
b11011 #
#280
b1111 %
1"
b11100 #
#290
0"
b11101 #
#300
b10000 %
1"
b11110 #
#310
0"
b11111 #
#320
b10001 %
1"
b100000 #
#330
0"
b100001 #
#340
b10010 %
1"
b100010 #
#350
0"
b100011 #
#360
b10011 %
1"
b100100 #
#370
0"
b100101 #
#380
b1110 !
b1110 $
b10100 %
1"
b100110 #
#390
0"
b100111 #
#400
b10101 %
1"
b101000 #
#410
0"
b101001 #
#420
b10110 %
1"
b101010 #
#430
0"
b101011 #
#440
b10111 %
1"
b101100 #
#450
0"
b101101 #
#460
b11000 %
1"
b101110 #
#470
0"
b101111 #
#480
b11001 %
1"
b110000 #
#490
0"
b110001 #
#500
b11010 %
1"
b110010 #
#510
0"
b110011 #
#520
b11011 %
1"
b110100 #
#530
0"
b110101 #
#540
b11100 %
1"
b110110 #
#550
0"
b110111 #
#560
b11101 %
1"
b111000 #
#570
0"
b111001 #
#580
b11110 %
1"
b111010 #
#590
0"
b111011 #
#600
b11111 %
1"
b111100 #
#610
0"
b111101 #
#620
b100000 %
1"
b111110 #
#630
0"
b111111 #
#640
b100001 %
1"
b1000000 #
#650
0"
b1000001 #
#660
b100010 %
1"
b1000010 #
#670
0"
b1000011 #
#680
b100011 %
1"
b1000100 #
#690
0"
b1000101 #
#700
b100100 %
1"
b1000110 #
#710
0"
b1000111 #
#720
b100101 %
1"
b1001000 #
#730
0"
b1001001 #
#740
b100110 %
1"
b1001010 #
#750
0"
b1001011 #
#760
b100111 %
1"
b1001100 #
#770
0"
b1001101 #
#780
b1100 !
b1100 $
b101000 %
1"
b1001110 #
#790
0"
b1001111 #
#800
b101001 %
1"
b1010000 #
#810
0"
b1010001 #
#820
b101010 %
1"
b1010010 #
#830
0"
b1010011 #
#840
b101011 %
1"
b1010100 #
#850
0"
b1010101 #
#860
b101100 %
1"
b1010110 #
#870
0"
b1010111 #
#880
b101101 %
1"
b1011000 #
#890
0"
b1011001 #
#900
b101110 %
1"
b1011010 #
#910
0"
b1011011 #
#920
b101111 %
1"
b1011100 #
#930
0"
b1011101 #
#940
b110000 %
1"
b1011110 #
#950
0"
b1011111 #
#960
b110001 %
1"
b1100000 #
#970
0"
b1100001 #
#980
b110010 %
1"
b1100010 #
#990
0"
b1100011 #
#1000
b110011 %
1"
b1100100 #
#1010
0"
b1100101 #
#1020
b110100 %
1"
b1100110 #
#1030
0"
b1100111 #
#1040
b110101 %
1"
b1101000 #
#1050
0"
b1101001 #
#1060
b110110 %
1"
b1101010 #
#1070
0"
b1101011 #
#1080
b110111 %
1"
b1101100 #
#1090
0"
b1101101 #
#1100
b111000 %
1"
b1101110 #
#1110
0"
b1101111 #
#1120
b111001 %
1"
b1110000 #
#1130
0"
b1110001 #
#1140
b111010 %
1"
b1110010 #
#1150
0"
b1110011 #
#1160
b111011 %
1"
b1110100 #
#1170
0"
b1110101 #
#1180
b1000 !
b1000 $
b111100 %
1"
b1110110 #
#1190
0"
b1110111 #
#1200
b111101 %
1"
b1111000 #
#1210
0"
b1111001 #
#1220
b111110 %
1"
b1111010 #
#1230
0"
b1111011 #
#1240
b111111 %
1"
b1111100 #
#1250
0"
b1111101 #
#1260
b1000000 %
1"
b1111110 #
#1270
0"
b1111111 #
#1280
b1000001 %
1"
b10000000 #
#1290
0"
b10000001 #
#1300
b1000010 %
1"
b10000010 #
#1310
0"
b10000011 #
#1320
b1000011 %
1"
b10000100 #
#1330
0"
b10000101 #
#1340
b1000100 %
1"
b10000110 #
#1350
0"
b10000111 #
#1360
b1000101 %
1"
b10001000 #
#1370
0"
b10001001 #
#1380
b1000110 %
1"
b10001010 #
#1390
0"
b10001011 #
#1400
b1000111 %
1"
b10001100 #
#1410
0"
b10001101 #
#1420
b1001000 %
1"
b10001110 #
#1430
0"
b10001111 #
#1440
b1001001 %
1"
b10010000 #
#1450
0"
b10010001 #
#1460
b1001010 %
1"
b10010010 #
#1470
0"
b10010011 #
#1480
b1001011 %
1"
b10010100 #
#1490
0"
b10010101 #
#1500
b1001100 %
1"
b10010110 #
#1510
0"
b10010111 #
#1520
b1001101 %
1"
b10011000 #
#1530
0"
b10011001 #
#1540
b1001110 %
1"
b10011010 #
#1550
0"
b10011011 #
#1560
b1001111 %
1"
b10011100 #
#1570
0"
b10011101 #
#1580
b0 !
b0 $
b1010000 %
1"
b10011110 #
#1590
0"
b10011111 #
#1600
b1010001 %
1"
b10100000 #
#1610
0"
b10100001 #
#1620
b1010010 %
1"
b10100010 #
#1630
0"
b10100011 #
#1640
b1010011 %
1"
b10100100 #
#1650
0"
b10100101 #
#1660
b1010100 %
1"
b10100110 #
#1670
0"
b10100111 #
#1680
b1010101 %
1"
b10101000 #
#1690
0"
b10101001 #
#1700
b1010110 %
1"
b10101010 #
#1710
0"
b10101011 #
#1720
b1010111 %
1"
b10101100 #
#1730
0"
b10101101 #
#1740
b1011000 %
1"
b10101110 #
#1750
0"
b10101111 #
#1760
b1011001 %
1"
b10110000 #
#1770
0"
b10110001 #
#1780
b1011010 %
1"
b10110010 #
#1790
0"
b10110011 #
#1800
b1011011 %
1"
b10110100 #
#1810
0"
b10110101 #
#1820
b1011100 %
1"
b10110110 #
#1830
0"
b10110111 #
#1840
b1011101 %
1"
b10111000 #
#1850
0"
b10111001 #
#1860
b1011110 %
1"
b10111010 #
#1870
0"
b10111011 #
#1880
b1011111 %
1"
b10111100 #
#1890
0"
b10111101 #
#1900
b1100000 %
1"
b10111110 #
#1910
0"
b10111111 #
#1920
b1100001 %
1"
b11000000 #
#1930
0"
b11000001 #
#1940
b1100010 %
1"
b11000010 #
#1950
0"
b11000011 #
#1960
b1100011 %
1"
b11000100 #
#1970
0"
b11000101 #
#1980
b1100100 %
1"
b11000110 #
#1990
0"
b11000111 #
#2000
b1111 !
b1111 $
b0 %
1"
b11001000 #
#2010
0"
b11001001 #
#2020
b1 %
1"
b11001010 #
#2030
0"
b11001011 #
#2040
b10 %
1"
b11001100 #
#2050
0"
b11001101 #
#2060
b11 %
1"
b11001110 #
#2070
0"
b11001111 #
#2080
b100 %
1"
b11010000 #
#2090
0"
b11010001 #
#2100
b101 %
1"
b11010010 #
#2110
0"
b11010011 #
#2120
b110 %
1"
b11010100 #
#2130
0"
b11010101 #
#2140
b111 %
1"
b11010110 #
#2150
0"
b11010111 #
#2160
b1000 %
1"
b11011000 #
#2170
0"
b11011001 #
#2180
b1001 %
1"
b11011010 #
#2190
0"
b11011011 #
#2200
b1010 %
1"
b11011100 #
#2210
0"
b11011101 #
#2220
b1011 %
1"
b11011110 #
#2230
0"
b11011111 #
#2240
b1100 %
1"
b11100000 #
#2250
0"
b11100001 #
#2260
b1101 %
1"
b11100010 #
#2270
0"
b11100011 #
#2280
b1110 %
1"
b11100100 #
#2290
0"
b11100101 #
#2300
b1111 %
1"
b11100110 #
#2310
0"
b11100111 #
#2320
b10000 %
1"
b11101000 #
#2330
0"
b11101001 #
#2340
b10001 %
1"
b11101010 #
#2350
0"
b11101011 #
#2360
b10010 %
1"
b11101100 #
#2370
0"
b11101101 #
#2380
b10011 %
1"
b11101110 #
#2390
0"
b11101111 #
#2400
b1110 !
b1110 $
b10100 %
1"
b11110000 #
#2410
0"
b11110001 #
#2420
b10101 %
1"
b11110010 #
#2430
0"
b11110011 #
#2440
b10110 %
1"
b11110100 #
#2450
0"
b11110101 #
#2460
b10111 %
1"
b11110110 #
#2470
0"
b11110111 #
#2480
b11000 %
1"
b11111000 #
#2490
0"
b11111001 #
#2500
b11001 %
1"
b11111010 #
#2510
0"
b11111011 #
#2520
b11010 %
1"
b11111100 #
#2530
0"
b11111101 #
#2540
b11011 %
1"
b11111110 #
#2550
0"
b11111111 #
#2560
b11100 %
1"
b100000000 #
#2570
0"
b100000001 #
#2580
b11101 %
1"
b100000010 #
#2590
0"
b100000011 #
#2600
b11110 %
1"
b100000100 #
#2610
0"
b100000101 #
#2620
b11111 %
1"
b100000110 #
#2630
0"
b100000111 #
#2640
b100000 %
1"
b100001000 #
#2650
0"
b100001001 #
#2660
b100001 %
1"
b100001010 #
#2670
0"
b100001011 #
#2680
b100010 %
1"
b100001100 #
#2690
0"
b100001101 #
#2700
b100011 %
1"
b100001110 #
#2710
0"
b100001111 #
#2720
b100100 %
1"
b100010000 #
#2730
0"
b100010001 #
#2740
b100101 %
1"
b100010010 #
#2750
0"
b100010011 #
#2760
b100110 %
1"
b100010100 #
#2770
0"
b100010101 #
#2780
b100111 %
1"
b100010110 #
#2790
0"
b100010111 #
#2800
b1100 !
b1100 $
b101000 %
1"
b100011000 #
#2810
0"
b100011001 #
#2820
b101001 %
1"
b100011010 #
#2830
0"
b100011011 #
#2840
b101010 %
1"
b100011100 #
#2850
0"
b100011101 #
#2860
b101011 %
1"
b100011110 #
#2870
0"
b100011111 #
#2880
b101100 %
1"
b100100000 #
#2890
0"
b100100001 #
#2900
b101101 %
1"
b100100010 #
#2910
0"
b100100011 #
#2920
b101110 %
1"
b100100100 #
#2930
0"
b100100101 #
#2940
b101111 %
1"
b100100110 #
#2950
0"
b100100111 #
#2960
b110000 %
1"
b100101000 #
#2970
0"
b100101001 #
#2980
b110001 %
1"
b100101010 #
#2990
0"
b100101011 #
#3000
b110010 %
1"
b100101100 #
#3010
0"
b100101101 #
#3020
b110011 %
1"
b100101110 #
#3030
0"
b100101111 #
#3040
b110100 %
1"
b100110000 #
#3050
0"
b100110001 #
#3060
b110101 %
1"
b100110010 #
#3070
0"
b100110011 #
#3080
b110110 %
1"
b100110100 #
#3090
0"
b100110101 #
#3100
b110111 %
1"
b100110110 #
#3110
0"
b100110111 #
#3120
b111000 %
1"
b100111000 #
#3130
0"
b100111001 #
#3140
b111001 %
1"
b100111010 #
#3150
0"
b100111011 #
#3160
b111010 %
1"
b100111100 #
#3170
0"
b100111101 #
#3180
b111011 %
1"
b100111110 #
#3190
0"
b100111111 #
#3200
b1000 !
b1000 $
b111100 %
1"
b101000000 #
#3210
0"
b101000001 #
#3220
b111101 %
1"
b101000010 #
#3230
0"
b101000011 #
#3240
b111110 %
1"
b101000100 #
#3250
0"
b101000101 #
#3260
b111111 %
1"
b101000110 #
#3270
0"
b101000111 #
#3280
b1000000 %
1"
b101001000 #
#3290
0"
b101001001 #
#3300
b1000001 %
1"
b101001010 #
#3310
0"
b101001011 #
#3320
b1000010 %
1"
b101001100 #
#3330
0"
b101001101 #
#3340
b1000011 %
1"
b101001110 #
#3350
0"
b101001111 #
#3360
b1000100 %
1"
b101010000 #
#3370
0"
b101010001 #
#3380
b1000101 %
1"
b101010010 #
#3390
0"
b101010011 #
#3400
b1000110 %
1"
b101010100 #
#3410
0"
b101010101 #
#3420
b1000111 %
1"
b101010110 #
#3430
0"
b101010111 #
#3440
b1001000 %
1"
b101011000 #
#3450
0"
b101011001 #
#3460
b1001001 %
1"
b101011010 #
#3470
0"
b101011011 #
#3480
b1001010 %
1"
b101011100 #
#3490
0"
b101011101 #
#3500
b1001011 %
1"
b101011110 #
#3510
0"
b101011111 #
#3520
b1001100 %
1"
b101100000 #
#3530
0"
b101100001 #
#3540
b1001101 %
1"
b101100010 #
#3550
0"
b101100011 #
#3560
b1001110 %
1"
b101100100 #
#3570
0"
b101100101 #
#3580
b1001111 %
1"
b101100110 #
#3590
0"
b101100111 #
#3600
b0 !
b0 $
b1010000 %
1"
b101101000 #
#3610
0"
b101101001 #
#3620
b1010001 %
1"
b101101010 #
#3630
0"
b101101011 #
#3640
b1010010 %
1"
b101101100 #
#3650
0"
b101101101 #
#3660
b1010011 %
1"
b101101110 #
#3670
0"
b101101111 #
#3680
b1010100 %
1"
b101110000 #
#3690
0"
b101110001 #
#3700
b1010101 %
1"
b101110010 #
#3710
0"
b101110011 #
#3720
b1010110 %
1"
b101110100 #
#3730
0"
b101110101 #
#3740
b1010111 %
1"
b101110110 #
#3750
0"
b101110111 #
#3760
b1011000 %
1"
b101111000 #
#3770
0"
b101111001 #
#3780
b1011001 %
1"
b101111010 #
#3790
0"
b101111011 #
#3800
b1011010 %
1"
b101111100 #
#3810
0"
b101111101 #
#3820
b1011011 %
1"
b101111110 #
#3830
0"
b101111111 #
#3840
b1011100 %
1"
b110000000 #
#3850
0"
b110000001 #
#3860
b1011101 %
1"
b110000010 #
#3870
0"
b110000011 #
#3880
b1011110 %
1"
b110000100 #
#3890
0"
b110000101 #
#3900
b1011111 %
1"
b110000110 #
#3910
0"
b110000111 #
#3920
b1100000 %
1"
b110001000 #
#3930
0"
b110001001 #
#3940
b1100001 %
1"
b110001010 #
#3950
0"
b110001011 #
#3960
b1100010 %
1"
b110001100 #
#3970
0"
b110001101 #
#3980
b1100011 %
1"
b110001110 #
#3990
0"
b110001111 #
#4000
b1100100 %
1"
b110010000 #
#4010
0"
b110010001 #
#4020
b1111 !
b1111 $
b0 %
1"
b110010010 #
#4030
0"
b110010011 #
#4040
b1 %
1"
b110010100 #
#4050
0"
b110010101 #
#4060
b10 %
1"
b110010110 #
#4070
0"
b110010111 #
#4080
b11 %
1"
b110011000 #
#4090
0"
b110011001 #
#4100
b100 %
1"
b110011010 #
#4110
0"
b110011011 #
#4120
b101 %
1"
b110011100 #
#4130
0"
b110011101 #
#4140
b110 %
1"
b110011110 #
#4150
0"
b110011111 #
#4160
b111 %
1"
b110100000 #
#4170
0"
b110100001 #
#4180
b1000 %
1"
b110100010 #
#4190
0"
b110100011 #
#4200
b1001 %
1"
b110100100 #
#4210
0"
b110100101 #
#4220
b1010 %
1"
b110100110 #
#4230
0"
b110100111 #
#4240
b1011 %
1"
b110101000 #
#4250
0"
b110101001 #
#4260
b1100 %
1"
b110101010 #
#4270
0"
b110101011 #
#4280
b1101 %
1"
b110101100 #
#4290
0"
b110101101 #
#4300
b1110 %
1"
b110101110 #
#4310
0"
b110101111 #
#4320
b1111 %
1"
b110110000 #
#4330
0"
b110110001 #
#4340
b10000 %
1"
b110110010 #
#4350
0"
b110110011 #
#4360
b10001 %
1"
b110110100 #
#4370
0"
b110110101 #
#4380
b10010 %
1"
b110110110 #
#4390
0"
b110110111 #
#4400
b10011 %
1"
b110111000 #
#4410
0"
b110111001 #
#4420
b1110 !
b1110 $
b10100 %
1"
b110111010 #
#4430
0"
b110111011 #
#4440
b10101 %
1"
b110111100 #
#4450
0"
b110111101 #
#4460
b10110 %
1"
b110111110 #
#4470
0"
b110111111 #
#4480
b10111 %
1"
b111000000 #
#4490
0"
b111000001 #
#4500
b11000 %
1"
b111000010 #
#4510
0"
b111000011 #
#4520
b11001 %
1"
b111000100 #
#4530
0"
b111000101 #
#4540
b11010 %
1"
b111000110 #
#4550
0"
b111000111 #
#4560
b11011 %
1"
b111001000 #
#4570
0"
b111001001 #
#4580
b11100 %
1"
b111001010 #
#4590
0"
b111001011 #
#4600
b11101 %
1"
b111001100 #
#4610
0"
b111001101 #
#4620
b11110 %
1"
b111001110 #
#4630
0"
b111001111 #
#4640
b11111 %
1"
b111010000 #
#4650
0"
b111010001 #
#4660
b100000 %
1"
b111010010 #
#4670
0"
b111010011 #
#4680
b100001 %
1"
b111010100 #
#4690
0"
b111010101 #
#4700
b100010 %
1"
b111010110 #
#4710
0"
b111010111 #
#4720
b100011 %
1"
b111011000 #
#4730
0"
b111011001 #
#4740
b100100 %
1"
b111011010 #
#4750
0"
b111011011 #
#4760
b100101 %
1"
b111011100 #
#4770
0"
b111011101 #
#4780
b100110 %
1"
b111011110 #
#4790
0"
b111011111 #
#4800
b100111 %
1"
b111100000 #
#4810
0"
b111100001 #
#4820
b1100 !
b1100 $
b101000 %
1"
b111100010 #
#4830
0"
b111100011 #
#4840
b101001 %
1"
b111100100 #
#4850
0"
b111100101 #
#4860
b101010 %
1"
b111100110 #
#4870
0"
b111100111 #
#4880
b101011 %
1"
b111101000 #
#4890
0"
b111101001 #
#4900
b101100 %
1"
b111101010 #
#4910
0"
b111101011 #
#4920
b101101 %
1"
b111101100 #
#4930
0"
b111101101 #
#4940
b101110 %
1"
b111101110 #
#4950
0"
b111101111 #
#4960
b101111 %
1"
b111110000 #
#4970
0"
b111110001 #
#4980
b110000 %
1"
b111110010 #
#4990
0"
b111110011 #
#5000
b110001 %
1"
b111110100 #
#5010
0"
b111110101 #
#5020
b110010 %
1"
b111110110 #
#5030
0"
b111110111 #
#5040
b110011 %
1"
b111111000 #
#5050
0"
b111111001 #
#5060
b110100 %
1"
b111111010 #
#5070
0"
b111111011 #
#5080
b110101 %
1"
b111111100 #
#5090
0"
b111111101 #
#5100
b110110 %
1"
b111111110 #
#5110
0"
b111111111 #
#5120
b110111 %
1"
b1000000000 #
#5130
0"
b1000000001 #
#5140
b111000 %
1"
b1000000010 #
#5150
0"
b1000000011 #
#5160
b111001 %
1"
b1000000100 #
#5170
0"
b1000000101 #
#5180
b111010 %
1"
b1000000110 #
#5190
0"
b1000000111 #
#5200
b111011 %
1"
b1000001000 #
#5210
0"
b1000001001 #
#5220
b1000 !
b1000 $
b111100 %
1"
b1000001010 #
#5230
0"
b1000001011 #
#5240
b111101 %
1"
b1000001100 #
#5250
0"
b1000001101 #
#5260
b111110 %
1"
b1000001110 #
#5270
0"
b1000001111 #
#5280
b111111 %
1"
b1000010000 #
#5290
0"
b1000010001 #
#5300
b1000000 %
1"
b1000010010 #
#5310
0"
b1000010011 #
#5320
b1000001 %
1"
b1000010100 #
#5330
0"
b1000010101 #
#5340
b1000010 %
1"
b1000010110 #
#5350
0"
b1000010111 #
#5360
b1000011 %
1"
b1000011000 #
#5370
0"
b1000011001 #
#5380
b1000100 %
1"
b1000011010 #
#5390
0"
b1000011011 #
#5400
b1000101 %
1"
b1000011100 #
#5410
0"
b1000011101 #
#5420
b1000110 %
1"
b1000011110 #
#5430
0"
b1000011111 #
#5440
b1000111 %
1"
b1000100000 #
#5450
0"
b1000100001 #
#5460
b1001000 %
1"
b1000100010 #
#5470
0"
b1000100011 #
#5480
b1001001 %
1"
b1000100100 #
#5490
0"
b1000100101 #
#5500
b1001010 %
1"
b1000100110 #
#5510
0"
b1000100111 #
#5520
b1001011 %
1"
b1000101000 #
#5530
0"
b1000101001 #
#5540
b1001100 %
1"
b1000101010 #
#5550
0"
b1000101011 #
#5560
b1001101 %
1"
b1000101100 #
#5570
0"
b1000101101 #
#5580
b1001110 %
1"
b1000101110 #
#5590
0"
b1000101111 #
#5600
b1001111 %
1"
b1000110000 #
#5610
0"
b1000110001 #
#5620
b0 !
b0 $
b1010000 %
1"
b1000110010 #
#5630
0"
b1000110011 #
#5640
b1010001 %
1"
b1000110100 #
#5650
0"
b1000110101 #
#5660
b1010010 %
1"
b1000110110 #
#5670
0"
b1000110111 #
#5680
b1010011 %
1"
b1000111000 #
#5690
0"
b1000111001 #
#5700
b1010100 %
1"
b1000111010 #
#5710
0"
b1000111011 #
#5720
b1010101 %
1"
b1000111100 #
#5730
0"
b1000111101 #
#5740
b1010110 %
1"
b1000111110 #
#5750
0"
b1000111111 #
#5760
b1010111 %
1"
b1001000000 #
#5770
0"
b1001000001 #
#5780
b1011000 %
1"
b1001000010 #
#5790
0"
b1001000011 #
#5800
b1011001 %
1"
b1001000100 #
#5810
0"
b1001000101 #
#5820
b1011010 %
1"
b1001000110 #
#5830
0"
b1001000111 #
#5840
b1011011 %
1"
b1001001000 #
#5850
0"
b1001001001 #
#5860
b1011100 %
1"
b1001001010 #
#5870
0"
b1001001011 #
#5880
b1011101 %
1"
b1001001100 #
#5890
0"
b1001001101 #
#5900
b1011110 %
1"
b1001001110 #
#5910
0"
b1001001111 #
#5920
b1011111 %
1"
b1001010000 #
#5930
0"
b1001010001 #
#5940
b1100000 %
1"
b1001010010 #
#5950
0"
b1001010011 #
#5960
b1100001 %
1"
b1001010100 #
#5970
0"
b1001010101 #
#5980
b1100010 %
1"
b1001010110 #
#5990
0"
b1001010111 #
#6000
b1100011 %
1"
b1001011000 #
#6010
0"
b1001011001 #
#6020
b1100100 %
1"
b1001011010 #
#6030
0"
b1001011011 #
#6040
b1111 !
b1111 $
b0 %
1"
b1001011100 #
#6050
0"
b1001011101 #
#6060
b1 %
1"
b1001011110 #
#6070
0"
b1001011111 #
#6080
b10 %
1"
b1001100000 #
#6090
0"
b1001100001 #
#6100
b11 %
1"
b1001100010 #
#6110
0"
b1001100011 #
#6120
b100 %
1"
b1001100100 #
#6130
0"
b1001100101 #
#6140
b101 %
1"
b1001100110 #
#6150
0"
b1001100111 #
#6160
b110 %
1"
b1001101000 #
#6170
0"
b1001101001 #
#6180
b111 %
1"
b1001101010 #
#6190
0"
b1001101011 #
#6200
b1000 %
1"
b1001101100 #
#6210
0"
b1001101101 #
#6220
b1001 %
1"
b1001101110 #
#6230
0"
b1001101111 #
#6240
b1010 %
1"
b1001110000 #
#6250
0"
b1001110001 #
#6260
b1011 %
1"
b1001110010 #
#6270
0"
b1001110011 #
#6280
b1100 %
1"
b1001110100 #
#6290
0"
b1001110101 #
#6300
b1101 %
1"
b1001110110 #
#6310
0"
b1001110111 #
#6320
b1110 %
1"
b1001111000 #
#6330
0"
b1001111001 #
#6340
b1111 %
1"
b1001111010 #
#6350
0"
b1001111011 #
#6360
b10000 %
1"
b1001111100 #
#6370
0"
b1001111101 #
#6380
b10001 %
1"
b1001111110 #
#6390
0"
b1001111111 #
#6400
b10010 %
1"
b1010000000 #
#6410
0"
b1010000001 #
#6420
b10011 %
1"
b1010000010 #
#6430
0"
b1010000011 #
#6440
b1110 !
b1110 $
b10100 %
1"
b1010000100 #
#6450
0"
b1010000101 #
#6460
b10101 %
1"
b1010000110 #
#6470
0"
b1010000111 #
#6480
b10110 %
1"
b1010001000 #
#6490
0"
b1010001001 #
#6500
b10111 %
1"
b1010001010 #
#6510
0"
b1010001011 #
#6520
b11000 %
1"
b1010001100 #
#6530
0"
b1010001101 #
#6540
b11001 %
1"
b1010001110 #
#6550
0"
b1010001111 #
#6560
b11010 %
1"
b1010010000 #
#6570
0"
b1010010001 #
#6580
b11011 %
1"
b1010010010 #
#6590
0"
b1010010011 #
#6600
b11100 %
1"
b1010010100 #
#6610
0"
b1010010101 #
#6620
b11101 %
1"
b1010010110 #
#6630
0"
b1010010111 #
#6640
b11110 %
1"
b1010011000 #
#6650
0"
b1010011001 #
#6660
b11111 %
1"
b1010011010 #
#6670
0"
b1010011011 #
#6680
b100000 %
1"
b1010011100 #
#6690
0"
b1010011101 #
#6700
b100001 %
1"
b1010011110 #
#6710
0"
b1010011111 #
#6720
b100010 %
1"
b1010100000 #
#6730
0"
b1010100001 #
#6740
b100011 %
1"
b1010100010 #
#6750
0"
b1010100011 #
#6760
b100100 %
1"
b1010100100 #
#6770
0"
b1010100101 #
#6780
b100101 %
1"
b1010100110 #
#6790
0"
b1010100111 #
#6800
b100110 %
1"
b1010101000 #
#6810
0"
b1010101001 #
#6820
b100111 %
1"
b1010101010 #
#6830
0"
b1010101011 #
#6840
b1100 !
b1100 $
b101000 %
1"
b1010101100 #
#6850
0"
b1010101101 #
#6860
b101001 %
1"
b1010101110 #
#6870
0"
b1010101111 #
#6880
b101010 %
1"
b1010110000 #
#6890
0"
b1010110001 #
#6900
b101011 %
1"
b1010110010 #
#6910
0"
b1010110011 #
#6920
b101100 %
1"
b1010110100 #
#6930
0"
b1010110101 #
#6940
b101101 %
1"
b1010110110 #
#6950
0"
b1010110111 #
#6960
b101110 %
1"
b1010111000 #
#6970
0"
b1010111001 #
#6980
b101111 %
1"
b1010111010 #
#6990
0"
b1010111011 #
#7000
b110000 %
1"
b1010111100 #
#7010
0"
b1010111101 #
#7020
b110001 %
1"
b1010111110 #
#7030
0"
b1010111111 #
#7040
b110010 %
1"
b1011000000 #
#7050
0"
b1011000001 #
#7060
b110011 %
1"
b1011000010 #
#7070
0"
b1011000011 #
#7080
b110100 %
1"
b1011000100 #
#7090
0"
b1011000101 #
#7100
b110101 %
1"
b1011000110 #
#7110
0"
b1011000111 #
#7120
b110110 %
1"
b1011001000 #
#7130
0"
b1011001001 #
#7140
b110111 %
1"
b1011001010 #
#7150
0"
b1011001011 #
#7160
b111000 %
1"
b1011001100 #
#7170
0"
b1011001101 #
#7180
b111001 %
1"
b1011001110 #
#7190
0"
b1011001111 #
#7200
b111010 %
1"
b1011010000 #
#7210
0"
b1011010001 #
#7220
b111011 %
1"
b1011010010 #
#7230
0"
b1011010011 #
#7240
b1000 !
b1000 $
b111100 %
1"
b1011010100 #
#7250
0"
b1011010101 #
#7260
b111101 %
1"
b1011010110 #
#7270
0"
b1011010111 #
#7280
b111110 %
1"
b1011011000 #
#7290
0"
b1011011001 #
#7300
b111111 %
1"
b1011011010 #
#7310
0"
b1011011011 #
#7320
b1000000 %
1"
b1011011100 #
#7330
0"
b1011011101 #
#7340
b1000001 %
1"
b1011011110 #
#7350
0"
b1011011111 #
#7360
b1000010 %
1"
b1011100000 #
#7370
0"
b1011100001 #
#7380
b1000011 %
1"
b1011100010 #
#7390
0"
b1011100011 #
#7400
b1000100 %
1"
b1011100100 #
#7410
0"
b1011100101 #
#7420
b1000101 %
1"
b1011100110 #
#7430
0"
b1011100111 #
#7440
b1000110 %
1"
b1011101000 #
#7450
0"
b1011101001 #
#7460
b1000111 %
1"
b1011101010 #
#7470
0"
b1011101011 #
#7480
b1001000 %
1"
b1011101100 #
#7490
0"
b1011101101 #
#7500
b1001001 %
1"
b1011101110 #
#7510
0"
b1011101111 #
#7520
b1001010 %
1"
b1011110000 #
#7530
0"
b1011110001 #
#7540
b1001011 %
1"
b1011110010 #
#7550
0"
b1011110011 #
#7560
b1001100 %
1"
b1011110100 #
#7570
0"
b1011110101 #
#7580
b1001101 %
1"
b1011110110 #
#7590
0"
b1011110111 #
#7600
b1001110 %
1"
b1011111000 #
#7610
0"
b1011111001 #
#7620
b1001111 %
1"
b1011111010 #
#7630
0"
b1011111011 #
#7640
b0 !
b0 $
b1010000 %
1"
b1011111100 #
#7650
0"
b1011111101 #
#7660
b1010001 %
1"
b1011111110 #
#7670
0"
b1011111111 #
#7680
b1010010 %
1"
b1100000000 #
#7690
0"
b1100000001 #
#7700
b1010011 %
1"
b1100000010 #
#7710
0"
b1100000011 #
#7720
b1010100 %
1"
b1100000100 #
#7730
0"
b1100000101 #
#7740
b1010101 %
1"
b1100000110 #
#7750
0"
b1100000111 #
#7760
b1010110 %
1"
b1100001000 #
#7770
0"
b1100001001 #
#7780
b1010111 %
1"
b1100001010 #
#7790
0"
b1100001011 #
#7800
b1011000 %
1"
b1100001100 #
#7810
0"
b1100001101 #
#7820
b1011001 %
1"
b1100001110 #
#7830
0"
b1100001111 #
#7840
b1011010 %
1"
b1100010000 #
#7850
0"
b1100010001 #
#7860
b1011011 %
1"
b1100010010 #
#7870
0"
b1100010011 #
#7880
b1011100 %
1"
b1100010100 #
#7890
0"
b1100010101 #
#7900
b1011101 %
1"
b1100010110 #
#7910
0"
b1100010111 #
#7920
b1011110 %
1"
b1100011000 #
#7930
0"
b1100011001 #
#7940
b1011111 %
1"
b1100011010 #
#7950
0"
b1100011011 #
#7960
b1100000 %
1"
b1100011100 #
#7970
0"
b1100011101 #
#7980
b1100001 %
1"
b1100011110 #
#7990
0"
b1100011111 #
#8000
b1100010 %
1"
b1100100000 #
#8010
0"
b1100100001 #
#8020
b1100011 %
1"
b1100100010 #
#8030
0"
b1100100011 #
#8040
b1100100 %
1"
b1100100100 #
