Ultrasonic/trigger.v
module trigger(
	input clk,
	output reg pulse=0
);

//Como tiempo LIMIT1 10us

parameter LIMIT1 = 9'd333; //Limit= 33.33MHz/(1/10us)=333
parameter SIZE1 = 9; // 10us/30ns=333.333 => log_2(333)=8.38=9


//Como tiempo LIMIT2 250ms

parameter LIMIT2 = 23'd8333333;
parameter SIZE2 = 23;


reg [1:0] count1 = 0;
reg [3:0] count2 = 0;

always@(posedge clk)
	begin
        if(count2<10)
        begin
            pulse = 0;
			count1 = 0;
            count2 = count2+1;
        end
        else
        begin
            if(count1<4)
			begin
                count2 = 0;
				count1 = count1+1;
				pulse = 1;
 //Se va a ir llenando un contador mientras el tiempo de 10us en que el ultrasonido
 //actua va emitiendo la señal de ultrasonido para que revote con la superficie que tenga al frente
			end 
        end		
	end
endmodule

Ultrasonic/trigger_tb.v
`timescale 1ns / 1ns
`include "trigger.v"

module trigger_tb;
    integer i;
    reg clk = 0;
    wire pulse;

    trigger uut(.clk(clk),.pulse(pulse));
            initial begin
            $dumpfile("trigger.vcd");
            $dumpvars(0, trigger_tb);
              for(i=0; i<100; i = i+1) begin
            clk = ~clk;
            #100; //Tiempo total del testbech 10 ns
    end
            $display("Test Complete uwu");
        end

endmodule

Ultrasonic/trigger.vcd
$date
	Fri May 03 16:01:44 2024
$end
$version
	Icarus Verilog
$end
$timescale
	1ns
$end
$scope module trigger_tb $end
$var wire 1 ! pulse $end
$var reg 1 " clk $end
$var integer 32 # i [31:0] $end
$scope module uut $end
$var wire 1 " clk $end
$var parameter 9 $ LIMIT1 $end
$var parameter 23 % LIMIT2 $end
$var parameter 32 & SIZE1 $end
$var parameter 32 ' SIZE2 $end
$var reg 2 ( count1 [1:0] $end
$var reg 4 ) count2 [3:0] $end
$var reg 1 ! pulse $end
$upscope $end
$upscope $end
$enddefinitions $end
$comment Show the parameter values. $end
$dumpall
b10111 '
b1001 &
b11111110010100000010101 %
b101001101 $
$end
#0
$dumpvars
b1 )
b0 (
b0 #
1"
0!
$end
#100
0"
b1 #
#200
b10 )
1"
b10 #
#300
0"
b11 #
#400
b11 )
1"
b100 #
#500
0"
b101 #
#600
b100 )
1"
b110 #
#700
0"
b111 #
#800
b101 )
1"
b1000 #
#900
0"
b1001 #
#1000
b110 )
1"
b1010 #
#1100
0"
b1011 #
#1200
b111 )
1"
b1100 #
#1300
0"
b1101 #
#1400
b1000 )
1"
b1110 #
#1500
0"
b1111 #
#1600
b1001 )
1"
b10000 #
#1700
0"
b10001 #
#1800
b1010 )
1"
b10010 #
#1900
0"
b10011 #
#2000
b1011 )
1"
b10100 #
#2100
0"
b10101 #
#2200
1!
b1 (
b0 )
1"
b10110 #
#2300
0"
b10111 #
#2400
b1 )
b0 (
0!
1"
b11000 #
#2500
0"
b11001 #
#2600
b10 )
1"
b11010 #
#2700
0"
b11011 #
#2800
b11 )
1"
b11100 #
#2900
0"
b11101 #
#3000
b100 )
1"
b11110 #
#3100
0"
b11111 #
#3200
b101 )
1"
b100000 #
#3300
0"
b100001 #
#3400
b110 )
1"
b100010 #
#3500
0"
b100011 #
#3600
b111 )
1"
b100100 #
#3700
0"
b100101 #
#3800
b1000 )
1"
b100110 #
#3900
0"
b100111 #
#4000
b1001 )
1"
b101000 #
#4100
0"
b101001 #
#4200
b1010 )
1"
b101010 #
#4300
0"
b101011 #
#4400
b1011 )
1"
b101100 #
#4500
0"
b101101 #
#4600
1!
b1 (
b0 )
1"
b101110 #
#4700
0"
b101111 #
#4800
b1 )
b0 (
0!
1"
b110000 #
#4900
0"
b110001 #
#5000
b10 )
1"
b110010 #
#5100
0"
b110011 #
#5200
b11 )
1"
b110100 #
#5300
0"
b110101 #
#5400
b100 )
1"
b110110 #
#5500
0"
b110111 #
#5600
b101 )
1"
b111000 #
#5700
0"
b111001 #
#5800
b110 )
1"
b111010 #
#5900
0"
b111011 #
#6000
b111 )
1"
b111100 #
#6100
0"
b111101 #
#6200
b1000 )
1"
b111110 #
#6300
0"
b111111 #
#6400
b1001 )
1"
b1000000 #
#6500
0"
b1000001 #
#6600
b1010 )
1"
b1000010 #
#6700
0"
b1000011 #
#6800
b1011 )
1"
b1000100 #
#6900
0"
b1000101 #
#7000
1!
b1 (
b0 )
1"
b1000110 #
#7100
0"
b1000111 #
#7200
b1 )
b0 (
0!
1"
b1001000 #
#7300
0"
b1001001 #
#7400
b10 )
1"
b1001010 #
#7500
0"
b1001011 #
#7600
b11 )
1"
b1001100 #
#7700
0"
b1001101 #
#7800
b100 )
1"
b1001110 #
#7900
0"
b1001111 #
#8000
b101 )
1"
b1010000 #
#8100
0"
b1010001 #
#8200
b110 )
1"
b1010010 #
#8300
0"
b1010011 #
#8400
b111 )
1"
b1010100 #
#8500
0"
b1010101 #
#8600
b1000 )
1"
b1010110 #
#8700
0"
b1010111 #
#8800
b1001 )
1"
b1011000 #
#8900
0"
b1011001 #
#9000
b1010 )
1"
b1011010 #
#9100
0"
b1011011 #
#9200
b1011 )
1"
b1011100 #
#9300
0"
b1011101 #
#9400
1!
b1 (
b0 )
1"
b1011110 #
#9500
0"
b1011111 #
#9600
b1 )
b0 (
0!
1"
b1100000 #
#9700
0"
b1100001 #
#9800
b10 )
1"
b1100010 #
#9900
0"
b1100011 #
#10000
b1100100 #
